nrt_logging/__init__.py
nrt_logging/config.py
nrt_logging/exceptions.py
nrt_logging/log_format.py
nrt_logging/log_level.py
nrt_logging/logger.py
nrt_logging/logger_manager.py
nrt_logging/logger_stream_handlers.py
nrt_logging-1.3.6.data/data/requirements.txt
nrt_logging-1.3.6.dist-info/LICENSE.md
nrt_logging-1.3.6.dist-info/METADATA
nrt_logging-1.3.6.dist-info/WHEEL
nrt_logging-1.3.6.dist-info/top_level.txt
nrt_logging-1.3.6.dist-info/RECORD
