Metadata-Version: 2.2
Name: nrt-logging
Version: 1.3.6
Summary: Hierarchical logging in yaml format
Home-page: https://github.com/etuzon/python-nrt-logging
Author: Eyal Tuzon
Author-email: Eyal Tuzon <eyal.tuzon.dev@gmail.com>
Project-URL: Homepage, https://github.com/etuzon/python-nrt-logging
Project-URL: Bug Tracker, https://github.com/etuzon/python-nrt-logging/issues
Project-URL: documentation, https://github.com/etuzon/python-nrt-logging/wiki
Keywords: python,python3,python-3,logging,logger,log,loggers,hierarchical,logging-library,logging-framework,hierarchy,yaml,nrt,nrt-logging
Classifier: Programming Language :: Python :: 3
Classifier: Programming Language :: Python :: 3.9
Classifier: Programming Language :: Python :: 3.10
Classifier: Programming Language :: Python :: 3.11
Classifier: Programming Language :: Python :: 3.12
Classifier: Programming Language :: Python :: 3.13
Classifier: License :: OSI Approved :: MIT License
Classifier: Operating System :: OS Independent
Requires-Python: >=3.9
License-File: LICENSE.md
Requires-Dist: PyYAML>=3.11
Requires-Dist: schema>=0.7.5
Dynamic: author
Dynamic: home-page
Dynamic: requires-dist
